LICENSE
MANIFEST.in
README.rst
setup.py
dj_mongo_reader.egg-info/PKG-INFO
dj_mongo_reader.egg-info/SOURCES.txt
dj_mongo_reader.egg-info/dependency_links.txt
dj_mongo_reader.egg-info/requires.txt
dj_mongo_reader.egg-info/top_level.txt
djmongoreader/__init__.py
djmongoreader/models.py
djmongoreader/mongoreader.py
djmongoreader/tests.py
djmongoreader/urls.py
djmongoreader/utility.py
djmongoreader/views.py
djmongoreader/static/dj-mongo-reader/js/mongoreader.js
djmongoreader/static/dj-mongo-reader/js/rendertable.js
djmongoreader/templates/dj-mongo-reader/core.html
djmongoreader/templates/dj-mongo-reader/table.html
example/.DS_Store
example/sampleapp/.DS_Store
example/sampleapp/Procfile
example/sampleapp/data_100.json
example/sampleapp/gen_testdata.py
example/sampleapp/manage.py
example/sampleapp/requirements.txt
example/sampleapp/.idea/.name
example/sampleapp/.idea/encodings.xml
example/sampleapp/.idea/misc.xml
example/sampleapp/.idea/modules.xml
example/sampleapp/.idea/sampleapp.iml
example/sampleapp/.idea/vcs.xml
example/sampleapp/.idea/workspace.xml
example/sampleapp/.idea/inspectionProfiles/Project_Default.xml
example/sampleapp/.idea/inspectionProfiles/profiles_settings.xml
example/sampleapp/.idea/scopes/scope_settings.xml
example/sampleapp/sampleapp/.DS_Store
example/sampleapp/sampleapp/__init__.py
example/sampleapp/sampleapp/__init__.pyc
example/sampleapp/sampleapp/security.py
example/sampleapp/sampleapp/security.pyc
example/sampleapp/sampleapp/settings.py
example/sampleapp/sampleapp/settings.pyc
example/sampleapp/sampleapp/urls.py
example/sampleapp/sampleapp/urls.pyc
example/sampleapp/sampleapp/views.py
example/sampleapp/sampleapp/views.pyc
example/sampleapp/sampleapp/wsgi.py
example/sampleapp/sampleapp/wsgi.pyc
example/sampleapp/templates/base.html
example/sampleapp/templates/query.html
example/sampleapp/templates/readme.html
example/sampleapp/templates/dj-mongo-reader/table.html